readme.rst
vibrationtesting/__init__.py
vibrationtesting/conftest.py
vibrationtesting/identification.py
vibrationtesting/signals.py
vibrationtesting/system.py
vibrationtesting/data/case1.mat
vibrationtesting/data/case2.mat
vibrationtesting/data/frf_data1.mat
vibrationtesting/data/mckiddat.mat
vibrationtesting/data/testdata.mat
vibrationtesting-0.24.dist-info/DESCRIPTION.rst
vibrationtesting-0.24.dist-info/METADATA
vibrationtesting-0.24.dist-info/RECORD
vibrationtesting-0.24.dist-info/WHEEL
vibrationtesting-0.24.dist-info/metadata.json
vibrationtesting-0.24.dist-info/top_level.txt
