Metadata-Version: 2.0
Name: vibrationtesting
Version: 0.24
Summary: Signal processing, modal analysis, plotting, and system                   identification for vibrating systems
Home-page: https://github.com/Vibration-Testing/vibrationtesting
Author: Joseph C. Slater
Author-email: joseph.c.slater@gmail.com
License: UNKNOWN
Keywords: vibration,mechanical engineering,testing,civil engineering,modal analysis
Platform: UNKNOWN
Requires-Dist: numpy
Requires-Dist: scipy
Requires-Dist: matplotlib
